CHANGES.md
LESSONS.md
MANIFEST.in
README.rst
requirements.txt
setup.py
IPython_Dashboard.egg-info/PKG-INFO
IPython_Dashboard.egg-info/SOURCES.txt
IPython_Dashboard.egg-info/dependency_links.txt
IPython_Dashboard.egg-info/entry_points.txt
IPython_Dashboard.egg-info/not-zip-safe
IPython_Dashboard.egg-info/requires.txt
IPython_Dashboard.egg-info/top_level.txt
dashboard/__init__.py
dashboard/client/__init__.py
dashboard/client/sender.py
dashboard/conf/__init__.py
dashboard/conf/config.py
dashboard/server/__init__.py
dashboard/server/start.py
dashboard/server/utils.py
dashboard/server/views.py
dashboard/server/resources/__init__.py
dashboard/server/resources/dash.py
dashboard/server/resources/home.py
dashboard/server/resources/share.py
dashboard/server/resources/sql.py
dashboard/server/resources/status.py
dashboard/server/resources/storage.py
dashboard/static/css/bootstrap-3.3.5.css
dashboard/static/css/bootstrap-3.3.5.min.css
dashboard/static/css/bootstrap-vertical-menu.css
dashboard/static/css/bootstrap.css.map
dashboard/static/css/bootstrap.min.css.map
dashboard/static/css/dash.css
dashboard/static/css/default.css
dashboard/static/css/font-awesome-4.4.0.css
dashboard/static/css/font-awesome-4.4.0.min.css
dashboard/static/css/gridstack.css
dashboard/static/css/jquery.gridster.css
dashboard/static/css/normalize.css
dashboard/static/css/nv.d3.css
dashboard/static/css/pygments.css
dashboard/static/fonts/fontawesome-webfont.woff
dashboard/static/fonts/fontawesome-webfont.woff2
dashboard/static/img/favicon.ico
dashboard/static/js/ace-1.2.0.js
dashboard/static/js/bootstrap-3.3.5.js
dashboard/static/js/bootstrap-3.3.5.min.js
dashboard/static/js/d3-3.5.6.js
dashboard/static/js/d3-3.5.6.min.js
dashboard/static/js/dash.js
dashboard/static/js/dash.sql.js
dashboard/static/js/dash.vis.js
dashboard/static/js/gridstack-0.2.4.js
dashboard/static/js/gridstack-0.2.4.min.js
dashboard/static/js/jquery-2.1.4.js
dashboard/static/js/jquery-2.1.4.min.js
dashboard/static/js/jquery-ui-1.11.4.js
dashboard/static/js/jquery-ui-1.11.4.min.js
dashboard/static/js/jquery-watch-1.16.js
dashboard/static/js/jquery.min.map
dashboard/static/js/jquery.tablesorter-2.23.5.js
dashboard/static/js/jquery.tablesorter-2.23.5.min.js
dashboard/static/js/lodash-3.10.1.js
