Metadata-Version: 1.1
Name: IPython-Dashboard
Version: 0.1.5
Summary: An stand alone, light-weight web server for building, sharing graphs in created in ipython. Let ipython do what it focus, let this do what everyone needs for building a interactive, collaborated and real-time streaming dashboards.
Home-page: https://github.com/litaotao/IPython-Dashboard
Author: Taotao Li
Author-email: taotao.engineer@gmail.com
License: BSD
Keywords: ipython,dashboard,interactive,visualization,data science,data analysis,streaming
Platform: UNKNOWN
Classifier: Intended Audience :: Science/Research
Classifier: Intended Audience :: Developers
Classifier: Programming Language :: Python
Classifier: Topic :: Software Development
Classifier: Topic :: Scientific/Engineering
Classifier: Operating System :: Microsoft :: Windows
Classifier: Operating System :: POSIX
Classifier: Operating System :: Unix
Classifier: Operating System :: MacOS
Classifier: Programming Language :: Python :: 2
Classifier: Programming Language :: Python :: 2.7
Classifier: Programming Language :: Python :: 3
Classifier: Programming Language :: Python :: 3.3
